reactivestreams/__init__.py
reactivestreams/publisher.py
reactivestreams/subscriber.py
reactivestreams/subscription.py
rsocket/__init__.py
rsocket/async_helpers.py
rsocket/datetime_helpers.py
rsocket/disposable.py
rsocket/error_codes.py
rsocket/exceptions.py
rsocket/fragment.py
rsocket/frame.py
rsocket/frame_builders.py
rsocket/frame_fragment_cache.py
rsocket/frame_fragmenter.py
rsocket/frame_helpers.py
rsocket/frame_logger.py
rsocket/frame_parser.py
rsocket/helpers.py
rsocket/lease.py
rsocket/local_typing.py
rsocket/logger.py
rsocket/payload.py
rsocket/queue_peekable.py
rsocket/request_handler.py
rsocket/rsocket.py
rsocket/rsocket_base.py
rsocket/rsocket_client.py
rsocket/rsocket_internal.py
rsocket/rsocket_server.py
rsocket/stream_control.py
rsocket/awaitable/__init__.py
rsocket/awaitable/awaitable_rsocket.py
rsocket/awaitable/collector_subscriber.py
rsocket/cli/__init__.py
rsocket/cli/command.py
rsocket/cloudevents/__init__.py
rsocket/cloudevents/serialize.py
rsocket/extensions/__init__.py
rsocket/extensions/authentication.py
rsocket/extensions/authentication_content.py
rsocket/extensions/authentication_types.py
rsocket/extensions/composite_metadata.py
rsocket/extensions/composite_metadata_item.py
rsocket/extensions/helpers.py
rsocket/extensions/mimetype.py
rsocket/extensions/mimetypes.py
rsocket/extensions/routing.py
rsocket/extensions/stream_data_mimetype.py
rsocket/extensions/tagging.py
rsocket/graphql/__init__.py
rsocket/graphql/rsocket_transport.py
rsocket/graphql/server_helper.py
rsocket/handlers/__init__.py
rsocket/handlers/interfaces.py
rsocket/handlers/request_cahnnel_common.py
rsocket/handlers/request_cahnnel_responder.py
rsocket/handlers/request_channel_requester.py
rsocket/handlers/request_response_requester.py
rsocket/handlers/request_response_responder.py
rsocket/handlers/request_stream_requester.py
rsocket/handlers/request_stream_responder.py
rsocket/load_balancer/__init__.py
rsocket/load_balancer/load_balancer_rsocket.py
rsocket-0.4.20.dist-info/licenses/LICENSE
rsocket-0.4.20.dist-info/METADATA
rsocket-0.4.20.dist-info/WHEEL
rsocket-0.4.20.dist-info/entry_points.txt
rsocket-0.4.20.dist-info/top_level.txt
rsocket-0.4.20.dist-info/RECORD
