Metadata-Version: 2.4
Name: rsocket
Version: 0.4.20
Summary: Python RSocket library
Home-page: https://github.com/rsocket/rsocket-py
Author: Gabriel Shaar
Author-email: workofishi@pm.me
License: MIT
Classifier: Development Status :: 4 - Beta
Classifier: Programming Language :: Python
Classifier: Programming Language :: Python :: 3.8
Classifier: Programming Language :: Python :: 3.9
Classifier: Programming Language :: Python :: 3.10
Classifier: Programming Language :: Python :: 3.11
Classifier: Programming Language :: Python :: 3.12
Classifier: Programming Language :: Python :: 3.13
Classifier: Environment :: Web Environment
Classifier: License :: OSI Approved :: MIT License
Classifier: Natural Language :: English
Classifier: Topic :: Internet :: WWW/HTTP :: Dynamic Content
Classifier: Topic :: Internet :: WWW/HTTP
Classifier: Topic :: Internet
Classifier: Topic :: Software Development :: Libraries :: Application Frameworks
Classifier: Topic :: Software Development :: Libraries :: Python Modules
Requires-Python: >=3.8
License-File: LICENSE
Provides-Extra: rx
Requires-Dist: Rx>=3.0.0; extra == "rx"
Provides-Extra: reactivex
Requires-Dist: reactivex>=4.0.0; extra == "reactivex"
Provides-Extra: aiohttp
Requires-Dist: aiohttp>=3.0.0; extra == "aiohttp"
Provides-Extra: quart
Requires-Dist: quart>=0.15.0; extra == "quart"
Provides-Extra: quic
Requires-Dist: aioquic>=0.9.0; extra == "quic"
Provides-Extra: cli
Requires-Dist: asyncclick>=8.0.0; extra == "cli"
Provides-Extra: optimized
Requires-Dist: cbitstruct>=1.1.0; extra == "optimized"
Provides-Extra: fastapi
Requires-Dist: fastapi>=0.115.0; extra == "fastapi"
Provides-Extra: cloudevents
Requires-Dist: cloudevents>=1.9.0; extra == "cloudevents"
Requires-Dist: pydantic>=1.10.0; extra == "cloudevents"
Provides-Extra: graphql
Requires-Dist: graphql-core>=3.2.0; extra == "graphql"
Requires-Dist: gql>=3.4.0; extra == "graphql"
Provides-Extra: websockets
Requires-Dist: websockets>=11.0.0; extra == "websockets"
Provides-Extra: channels
Requires-Dist: channels>=4.0.0; extra == "channels"
Requires-Dist: daphne>=4.1.2; extra == "channels"
Provides-Extra: asyncwebsockets
Requires-Dist: asyncwebsockets>=0.9.4; extra == "asyncwebsockets"
Dynamic: license-file
